scarp/__init__.py
scarp/data_prepare.py
scarp/help_func.py
scarp/model.py
scarp-1.0.0.dist-info/LICENSE
scarp-1.0.0.dist-info/METADATA
scarp-1.0.0.dist-info/WHEEL
scarp-1.0.0.dist-info/top_level.txt
scarp-1.0.0.dist-info/RECORD
