Metadata-Version: 2.1
Name: scarp
Version: 1.0.0
Summary: Incorporating network diffusion and peak location information for better single-cell ATAC-seq data analysis
Home-page: https://github.com/Wu-lab/SCARP
Author: Jiating Yu
Author-email: yujiating@amss.ac.cn
Requires-Python: >=3.10
License-File: LICENSE
Requires-Dist: scanpy >=1.9.5
Requires-Dist: pandas >=2.1.1
Requires-Dist: numpy >=1.25.2
Requires-Dist: scipy >=1.11.3
